{"count": 10, "updated": 0, "group_ids": [{"fiction_ids": [345220, 321076, 319198, 323942, 316804, 323124, 320654, 315897, 270829, 315346, 322734, 306643, 317745, 274700, 316243, 322697], "name": ""}], "description": "女：亲爱的，我好冷！\n男票：快到我怀里来", "hidden_info": "H5", "gender": 0, "v": 0, "label": "冬日暖文：零下十度的温暖，唯有爱可以给你", "result": 0, "list_id": 11527, "total": 0, "items": [{"latest": "第1074章 小剧场：坑娃小花生", "ad": 0, "updated": 1486575676, "word_count": 1101680, "owner": 0, "auth_device": [960, 1, 2, 3, 4, 5, 6, 7, 8, 105, 106, 103, 104, 950, 900, 102, 101], "allow_discount": 0, "ad_time": 0, "click": 25974705, "free_chapter": false, "score_count": 1561, "qmss_popular": 201890, "title": "那时喜欢你", "subscribe_discount": 5, "new_tags": ["甜文", "总裁", "吃货", "契约", "青梅竹马"], "on_sale": true, "hot": 28831922, "has_ad": 0, "ad_duration": 0, "comment_count": 927, "score": 9.33, "allow_free_read": 1, "rights_id": 10080, "qmss_score": 9.33, "channel": [2], "latest_created": 0, "finish": true, "rec_words": "姓名:秦芷爱，职位：顾余生的妻子", "tags": ["现代言情", "豪门世家"], "price": 5, "chapter_count": 1074, "authors": "叶非夜", "categories": [{"category_id": 18000000, "label": "现代言情"}, {"category_id": 18000700, "label": "豪门世家"}], "vip_status": 0, "copyright": "", "rights": "阅文集团旗下云起书院", "level": 0, "cover": "http://cover.read.duokan.com/mfsv2/download/fdsc3/p01eZs8Jyaov/5OxoSzkLjSKzKF.jpg", "summary": "一场意外，她和他睡在一起，两个月后她怀孕，他和她奉子成婚。\r\n“顾先生，我喜欢这家的菜。”这家的厨师...", "qmss_read": 126992, "fiction_id": 345220, "outer_id": "4963221703427703", "latest_id": 1074}, {"latest": "番外 输了", "ad": 0, "updated": 1471428641, "word_count": 1352135, "owner": 0, "auth_device": [960, 1, 2, 3, 4, 5, 6, 7, 8, 106, 103, 104, 950, 900, 102, 101], "allow_discount": 0, "ad_time": 0, "click": 3331069, "free_chapter": false, "score_count": 83, "qmss_popular": 79625, "title": "豪门暖媳", "subscribe_discount": 5, "on_sale": true, "hot": 3697486, "has_ad": 0, "ad_duration": 0, "comment_count": 64, "score": 8.24, "allow_free_read": 1, "rights_id": 10039, "qmss_score": 8.24, "channel": [2], "latest_created": 0, "finish": true, "tags": ["豪门暖媳", "总裁世家", "总裁豪门", "现代言情", "豪门世家"], "price": 5, "chapter_count": 248, "authors": "浮光锦", "categories": [{"category_id": 120000, "label": "总裁世家"}, {"category_id": 120100, "label": "总裁豪门"}, {"category_id": 18000000, "label": "现代言情"}, {"category_id": 18000700, "label": "豪门世家"}], "vip_status": 0, "copyright": "", "rights": "潇湘书院", "level": 0, "cover": "http://cover.read.duokan.com/mfsv2/download/fdsc3/p01dYhcJnCy9/qP7ebwYmyeQQW4.jpg", "summary": "晏少卿，京城晏家三公子，国内医学界最年轻的脑外科教授，晏少卿见过他的未来媳妇儿两次，第一次，他八岁，...", "qmss_read": 50766, "fiction_id": 321076, "outer_id": "5728793d50e3a4517cbed2a7", "latest_id": 247}, {"latest": "不求同日生，但要白头老", "ad": 0, "updated": 1465725062, "word_count": 1767293, "owner": 0, "auth_device": [960, 1, 2, 3, 4, 5, 6, 7, 8, 105, 106, 103, 104, 950, 900, 102, 101], "allow_discount": 0, "ad_time": 0, "click": 4888700, "free_chapter": false, "score_count": 73, "qmss_popular": 68888, "title": "闪婚甜妻，总裁大人难伺候！", "subscribe_discount": 5, "on_sale": true, "hot": 5426457, "has_ad": 0, "ad_duration": 0, "comment_count": 49, "score": 8.49, "allow_free_read": 1, "rights_id": 20002, "qmss_score": 8.49, "channel": [2], "latest_created": 0, "finish": true, "rec_words": "高富帅总裁与二傻娇妻有爱的故事。", "tags": ["总裁世家", "总裁豪门", "现代言情", "豪门世家"], "price": 3, "chapter_count": 543, "authors": "爷爷爷爷爷", "categories": [{"category_id": 120000, "label": "总裁世家"}, {"category_id": 120100, "label": "总裁豪门"}, {"category_id": 18000000, "label": "现代言情"}, {"category_id": 18000700, "label": "豪门世家"}], "vip_status": 0, "copyright": "", "rights": "红袖", "level": 0, "cover": "http://cover.read.duokan.com/mfsv2/download/fdsc3/p01Gc9ThQJwN/bBnWXyV77SEJ2s.jpg", "summary": "她做梦也没想到那个男人竟是她素未谋面的老公！\r\n父亲为了公司把她嫁给传说中又老又丑的男人，婚期三年。", "qmss_read": 44062, "fiction_id": 319198, "outer_id": "56fa4fdb50e3a4634152501c", "latest_id": 542}, {"latest": "番外-陈洋&李美", "ad": 0, "updated": 1469609018, "word_count": 458018, "owner": 0, "auth_device": [960, 1, 2, 3, 4, 5, 6, 7, 8, 105, 106, 103, 104, 950, 900, 102, 101], "allow_discount": 0, "ad_time": 0, "click": 867152, "free_chapter": false, "score_count": 108, "qmss_popular": 86512, "title": "宠婚", "subscribe_discount": 5, "on_sale": true, "hot": 962538, "has_ad": 0, "ad_duration": 0, "comment_count": 62, "score": 8.35, "allow_free_read": 1, "rights_id": 20004, "qmss_score": 8.35, "channel": [2], "latest_created": 0, "finish": true, "tags": ["原创", "言情", "近代现代", "爱情", "现代言情", "都市言情", "都市生活"], "price": 3, "chapter_count": 127, "authors": "李息隐", "categories": [{"category_id": 100000, "label": "现代言情"}, {"category_id": 100100, "label": "都市言情"}, {"category_id": 18000000, "label": "现代言情"}, {"category_id": 18000100, "label": "都市生活"}], "vip_status": 0, "copyright": "", "rights": "晋江文学", "level": 0, "cover": "http://cover.read.duokan.com/mfsv2/download/fdsc3/p01j82i4stQU/HIu5gAIH1s4UK5.jpg", "summary": "结婚前，她跟江驰不熟，觉得他为人冷漠不苟言笑，想来是不会热衷于那方面的事情。\n结婚后，她才知道，男人...", "qmss_read": 55060, "fiction_id": 323942, "outer_id": "2586293", "latest_id": 126}, {"latest": "全书大结局+新书已发", "ad": 0, "updated": 1537964928, "word_count": 5300263, "owner": 0, "auth_device": [960, 1, 2, 3, 4, 5, 6, 7, 8, 105, 106, 103, 104, 950, 900, 102, 101], "allow_discount": false, "ad_time": 0, "click": 19534064, "free_chapter": false, "score_count": 646, "qmss_popular": 151688, "title": "豪门暖婚蜜爱", "subscribe_discount": 5, "new_tags": ["甜文", "总裁", "腹黑", "冰山", "豪门", "日久生情"], "on_sale": true, "hot": 21682811, "has_ad": 0, "ad_duration": 0, "comment_count": 394, "score": 8.3, "allow_free_read": 1, "rights_id": 10080, "qmss_score": 8.3, "channel": [2], "latest_created": 1537964928, "finish": true, "tags": ["宠文", "总裁", "冤家", "温雨瓷", "总裁世家", "总裁豪门", "现代言情", "豪门世家"], "price": 5, "chapter_count": 2220, "authors": "百里夜星", "categories": [{"category_id": 120000, "label": "总裁世家"}, {"category_id": 120100, "label": "总裁豪门"}, {"category_id": 18000000, "label": "现代言情"}, {"category_id": 18000700, "label": "豪门世家"}], "vip_status": 0, "copyright": "", "rights": "阅文集团旗下小说阅读网", "level": 0, "cover": "http://cover.read.duokan.com/mfsv2/download/fdsc3/p01Q3gRNlUgL/5qzWBbidBFPaPi.jpg", "summary": "十三年前，她大雪中救他，十三年后，他害她家破人亡，走投无路时，他逼她做他的女人，她转身走向另外一个男...", "qmss_read": 95694, "fiction_id": 316804, "outer_id": "25389712000663101", "latest_id": 2913}, {"latest": "第628章 女儿出生（大结局）", "ad": 0, "updated": 1512554532, "word_count": 1286409, "owner": 0, "auth_device": [960, 1, 2, 3, 4, 5, 6, 7, 8, 105, 106, 103, 104, 950, 900, 102, 101], "allow_discount": 0, "ad_time": 0, "click": 10110605, "free_chapter": false, "score_count": 419, "qmss_popular": 107805, "title": "霸道宠婚：老婆，你被潜了", "subscribe_discount": 5, "new_tags": ["宠文", "总裁", "宝宝", "一见钟情"], "on_sale": true, "hot": 11222771, "has_ad": 0, "ad_duration": 0, "comment_count": 210, "score": 8.09, "allow_free_read": 1, "rights_id": 10080, "qmss_score": 8.09, "channel": [2], "latest_created": 0, "finish": true, "tags": ["现代言情", "豪门世家"], "price": 5, "chapter_count": 628, "authors": "无尽相思", "categories": [{"category_id": 18000000, "label": "现代言情"}, {"category_id": 18000700, "label": "豪门世家"}], "vip_status": 0, "copyright": "", "rights": "阅文集团旗下云起书院", "level": 0, "cover": "http://cover.read.duokan.com/mfsv2/download/fdsc3/p01AYhpJtOOW/CktdmKJk0uzHWW.jpg", "summary": "“老婆，我还要……”\r\n午夜，他偷进她的房间，将她压在身下，强行吃干抹净。隔天却耍赖不认：“我八成是...", "qmss_read": 68335, "fiction_id": 323124, "outer_id": "4266285504772903", "latest_id": 627}, {"latest": "第1046章 大结局", "ad": 0, "updated": 1550849830, "word_count": 2159865, "owner": 0, "auth_device": [960, 1, 2, 3, 4, 5, 6, 7, 8, 105, 106, 103, 104, 950, 900, 102, 101], "allow_discount": 0, "ad_time": 0, "click": 8747920, "free_chapter": false, "score_count": 145, "qmss_popular": 81937, "title": "婚然心动：甜妻限时购", "subscribe_discount": 5, "new_tags": ["甜文", "总裁", "萌系", "宝宝", "隐婚"], "on_sale": true, "hot": 9710191, "has_ad": 0, "ad_duration": 0, "comment_count": 88, "score": 7.95, "allow_free_read": 1, "rights_id": 10080, "qmss_score": 7.95, "channel": [2], "latest_created": 1550849630, "finish": true, "rec_words": "某少的婚后生活：白天有宠溺，晚上有体力，爱她就要爱彻底。", "tags": ["现代言情", "豪门世家"], "price": 5, "chapter_count": 1065, "authors": "柚子蜜", "categories": [{"category_id": 18000000, "label": "现代言情"}, {"category_id": 18000700, "label": "豪门世家"}], "vip_status": 0, "copyright": "", "rights": "阅文集团旗下云起书院", "level": 0, "cover": "http://cover.read.duokan.com/mfsv2/download/fdsc3/p01FLtcgY5fD/hnfVZWWFnlqBeJ.jpg", "summary": "惨遭未婚夫劈腿，她被逼嫁给了一个“一穷二白”的男人。\r\n人前，他是三无人员：无车，无房，无存款；\r\n...", "qmss_read": 52207, "fiction_id": 320654, "outer_id": "22418095000194302", "latest_id": 1066}, {"latest": "第635章", "ad": 0, "updated": 1451363104, "word_count": 1163573, "owner": 0, "auth_device": [960, 1, 2, 3, 4, 5, 6, 7, 8, 106, 103, 104, 950, 900, 102, 101], "allow_discount": 0, "ad_time": 0, "click": 12706088, "free_chapter": false, "score_count": 249, "qmss_popular": 87199, "title": "缘嫁首长老公", "subscribe_discount": 5, "on_sale": true, "hot": 14103757, "has_ad": 0, "ad_duration": 0, "comment_count": 154, "score": 8.22, "allow_free_read": 1, "rights_id": 10020, "qmss_score": 8.22, "channel": [2], "latest_created": 0, "finish": true, "tags": ["豪门", "高干", "军婚", "酷男", "先婚后爱", "宠文", "总裁世家", "总裁豪门", "现代言情", "豪门世家"], "price": 3, "chapter_count": 635, "authors": "垚星辰", "categories": [{"category_id": 120000, "label": "总裁世家"}, {"category_id": 120100, "label": "总裁豪门"}, {"category_id": 18000000, "label": "现代言情"}, {"category_id": 18000700, "label": "豪门世家"}], "vip_status": 0, "copyright": "", "rights": "小说阅读网", "level": 0, "cover": "http://cover.read.duokan.com/mfsv2/download/s010/p01L6iIh9fj0/nZfYoEQ4ZlrXg2.jpg", "summary": "他家世显赫，是A市最有价值的钻石级单身汉，但是也是长辈眼中的“剩男”，所以他缺一位妻子。她，资深婚礼...", "qmss_read": 55488, "fiction_id": 315897, "outer_id": "567a670050e3a41b2e087b89", "latest_id": 634}, {"latest": "第两千零八十八章：番外288", "ad": 0, "updated": 1552025787, "word_count": 2152953, "owner": 0, "auth_device": [960, 1, 2, 3, 4, 5, 6, 7, 8, 105, 106, 103, 104, 950, 900, 102, 101], "allow_discount": false, "ad_time": 0, "click": 99472547, "free_chapter": false, "score_count": 4253, "qmss_popular": 287036, "title": "爆萌宠妃", "subscribe_discount": 5, "on_sale": true, "hot": 110414527, "has_ad": 0, "ad_duration": 0, "comment_count": 3266, "score": 8.61, "allow_free_read": 1, "rights_id": 10080, "qmss_score": 8.61, "channel": [2], "latest_created": 1552025777, "finish": true, "tags": ["架空穿越", "穿越架空", "古代言情", "穿越奇情"], "price": 5, "chapter_count": 2075, "authors": "夜清歌", "categories": [{"category_id": 130000, "label": "穿越架空"}, {"category_id": 130100, "label": "架空穿越"}, {"category_id": 17000000, "label": "古代言情"}, {"category_id": 17000400, "label": "穿越奇情"}], "vip_status": 0, "copyright": "", "rights": "阅文集团旗下云起书院", "level": 0, "cover": "http://cover.read.duokan.com/mfsv2/download/fdsc3/p01TgfCoAZoT/QZsTzPxtpSI7lx.jpg", "summary": "“王爷，王妃休书一封，请您签收。”某王掀桌：“还反了她不成！”夜总会，混赌场，斗王爷，看她如何玩转古", "qmss_read": 180076, "fiction_id": 270829, "outer_id": "22175450000399302", "latest_id": 2077}, {"latest": "大结局", "ad": 0, "updated": 1463123220, "word_count": 632315, "owner": 0, "auth_device": [960, 1, 2, 3, 4, 5, 6, 7, 8, 105, 106, 103, 104, 950, 900, 102, 101], "allow_discount": 0, "ad_time": 0, "click": 6354971, "free_chapter": false, "score_count": 1083, "qmss_popular": 88604, "title": "一宠成婚", "subscribe_discount": 5, "on_sale": true, "hot": 7054017, "has_ad": 0, "ad_duration": 0, "comment_count": 609, "score": 8.88, "allow_free_read": 1, "rights_id": 20004, "qmss_score": 8.88, "channel": [2], "latest_created": 0, "finish": true, "rec_words": "超宠现言，百万点击阅读量！嫁给他是个意外，却没想到，陆皓谦向来低调惯了，唯有宠她，总是格外高调~", "tags": ["原创", "言情", "近代现代", "爱情", "现代言情", "都市言情", "都市生活"], "price": 3, "chapter_count": 177, "authors": "景诺", "categories": [{"category_id": 100000, "label": "现代言情"}, {"category_id": 100100, "label": "都市言情"}, {"category_id": 18000000, "label": "现代言情"}, {"category_id": 18000100, "label": "都市生活"}], "vip_status": 0, "copyright": "", "rights": "晋江文学", "level": 0, "cover": "http://cover.read.duokan.com/mfsv2/download/s010/p01Ji9eDTXqC/86WxUJ9MtjWjHY.jpg", "summary": "遇到身份背景不明又不太与人亲近的陆皓谦，对顾烟来说是个意外。 \n找了个没房没车的穷人，父母要和她决裂...", "qmss_read": 56364, "fiction_id": 315346, "outer_id": "2455652", "latest_id": 176}], "banner": "http://image.read.duokan.com/mfsv2/download/fdsc3/p014AeXQo870/lDTp6p4GryWm1G.jpg", "packed": false, "more": true}